pretix_przelewy24/__init__.py
pretix_przelewy24/apps.py
pretix_przelewy24/payment.py
pretix_przelewy24/signals.py
pretix_przelewy24/urls.py
pretix_przelewy24/views.py
pretix_przelewy24/locale/de/LC_MESSAGES/django.mo
pretix_przelewy24/locale/de/LC_MESSAGES/django.po
pretix_przelewy24/locale/de_Informal/.gitkeep
pretix_przelewy24/locale/de_Informal/LC_MESSAGES/django.mo
pretix_przelewy24/locale/de_Informal/LC_MESSAGES/django.po
pretix_przelewy24/static/pretix_przelewy24/.gitkeep
pretix_przelewy24/static/pretix_przelewy24/przelewy24_logo.svg
pretix_przelewy24/static/pretix_przelewy24/style.css
pretix_przelewy24/templates/pretix_przelewy24/.gitkeep
pretix_przelewy24/templates/pretix_przelewy24/checkout_confirm_render.html
pretix_przelewy24/templates/pretix_przelewy24/checkout_payment_form.html
pretix_przelewy24/templates/pretix_przelewy24/control.html
pretix_przelewy24-1.0.0.dist-info/LICENSE
pretix_przelewy24-1.0.0.dist-info/METADATA
pretix_przelewy24-1.0.0.dist-info/WHEEL
pretix_przelewy24-1.0.0.dist-info/entry_points.txt
pretix_przelewy24-1.0.0.dist-info/top_level.txt
pretix_przelewy24-1.0.0.dist-info/RECORD
