Metadata-Version: 2.1
Name: pretix-przelewy24
Version: 1.0.0
Summary: Accept payments through Przelewy24, a Polish payment facilitator.
Author-email: pretix team <support@pretix.eu>
Maintainer-email: pretix team <support@pretix.eu>
License: Apache
Project-URL: homepage, https://github.com/pretix/pretix-przelewy24
Project-URL: repository, https://github.com/pretix/pretix-przelewy24
Keywords: pretix
License-File: LICENSE
